{
    "data": [
        {
            "author_id": "27989519",
            "created_at": "2011-07-22T23:53:30.000Z",
            "geo": {
                "place_id": "eec8e86da985fc44"
            },
            "id": "94555699404742656",
            "text": "@AZsoul @TaysLadybug  according to Nick his father used to work with Sal and Nick at on the NFPD but is retired"
        },
        {
            "author_id": "27989519",
            "created_at": "2011-07-22T23:52:48.000Z",
            "geo": {
                "place_id": "eec8e86da985fc44"
            },
            "id": "94555524661653504",
            "text": "@TaysLadybug @AZsoul thing is one of the guys that installed the air conditioner w works with my nephew at the sheriffs dept LOL"
        },
        {
            "author_id": "27989519",
            "created_at": "2011-07-22T23:51:34.000Z",
            "geo": {
                "place_id": "eec8e86da985fc44"
            },
            "id": "94555215944101888",
            "text": "@TaysLadybug @AZsoul  funny thing is I was playing popit on Pogo and didn't notice any of your tweets til no\u2026 (cont) http://deck.ly/~9GzLY"
        },
        {
            "author_id": "218121199",
            "created_at": "2011-07-22T23:51:34.000Z",
            "geo": {
                "place_id": "3645adf266c57704"
            },
            "id": "94555213322665984",
            "text": "http://t.co/Q5XsJZX SvenD|TV Starting Now!"
        },
        {
            "author_id": "76330021",
            "created_at": "2011-07-22T23:48:15.000Z",
            "geo": {
                "place_id": "eec8e86da985fc44"
            },
            "id": "94554377938939904",
            "text": "Im high so nothin aint far fetched #@redcafeSD"
        },
        {
            "author_id": "27989519",
            "created_at": "2011-07-22T23:22:56.000Z",
            "geo": {
                "place_id": "eec8e86da985fc44"
            },
            "id": "94548007730679808",
            "text": "@AZsoul me either"
        },
        {
            "author_id": "218121199",
            "created_at": "2011-07-22T23:21:57.000Z",
            "geo": {
                "place_id": "3645adf266c57704"
            },
            "id": "94547762129022977",
            "text": "Viewers already starting to pour into SvenD|TV Podcast...The SvenD Army Is Showing Up Like Always.  Much Love!"
        },
        {
            "author_id": "218121199",
            "created_at": "2011-07-22T23:21:24.000Z",
            "geo": {
                "place_id": "3645adf266c57704"
            },
            "id": "94547620592226304",
            "text": "SvenD|TV Ep. 5 Feat. TheHardlineReport's Nappyboy and BigCountry Starting @ 8p.m. EST [40 Mins]!  http://t.co/Q5XsJZX"
        },
        {
            "author_id": "27989519",
            "created_at": "2011-07-22T23:19:27.000Z",
            "geo": {
                "place_id": "eec8e86da985fc44"
            },
            "id": "94547129963515905",
            "text": "@AZsoul  LOL I guess he wasn't piloting it but who knows he prolly knows how"
        },
        {
            "author_id": "27989519",
            "created_at": "2011-07-22T23:18:21.000Z",
            "geo": {
                "place_id": "eec8e86da985fc44"
            },
            "id": "94546855291142144",
            "text": "@TaysLadybug yes but a window conditioner that works would work better than a central unit that doesn't work!"
        },
        {
            "author_id": "27989519",
            "created_at": "2011-07-22T23:17:00.000Z",
            "geo": {
                "place_id": "eec8e86da985fc44"
            },
            "id": "94546515300843520",
            "text": "@AZsoul thank you Denise"
        },
        {
            "author_id": "27989519",
            "created_at": "2011-07-22T23:15:49.000Z",
            "geo": {
                "place_id": "eec8e86da985fc44"
            },
            "id": "94546215903039489",
            "text": "@AZsoul @AZsoul LOL 4 a minute at the end of  shotgun video I thought @taylorRHicks was piloting the plane whe\u2026 (cont) http://deck.ly/~DRgHC"
        },
        {
            "author_id": "22044873",
            "created_at": "2011-07-22T22:31:16.000Z",
            "geo": {
                "place_id": "3645adf266c57704"
            },
            "id": "94535006332002304",
            "text": "SEO Tip: Stay focused on specific key words and phrases within each article or post."
        },
        {
            "author_id": "34079123",
            "created_at": "2011-07-22T22:24:29.000Z",
            "geo": {
                "place_id": "eec8e86da985fc44"
            },
            "id": "94533298386247681",
            "text": "RT @JoNEsyCatt: Just saw my man @TeamLateef slaving\" haha bro gotta buy school clothes so i gotta do what i gotta do lol !!"
        },
        {
            "author_id": "17880088",
            "created_at": "2011-07-22T22:11:37.000Z",
            "geo": {
                "place_id": "eec8e86da985fc44"
            },
            "id": "94530063109853185",
            "text": "Just keep telling myself only three hours left...."
        },
        {
            "author_id": "27989519",
            "created_at": "2011-07-22T21:42:23.000Z",
            "geo": {
                "place_id": "eec8e86da985fc44"
            },
            "id": "94522703175884800",
            "text": "@TaysLadybug why do they cost more to run of course this thing has been running and running and not going down ok got to get dinner  ttyl"
        },
        {
            "author_id": "27989519",
            "created_at": "2011-07-22T21:40:18.000Z",
            "geo": {
                "place_id": "eec8e86da985fc44"
            },
            "id": "94522178317459456",
            "text": "@onesoul63 Your welcome me too"
        },
        {
            "author_id": "27989519",
            "created_at": "2011-07-22T21:39:00.000Z",
            "geo": {
                "place_id": "eec8e86da985fc44"
            },
            "id": "94521854093565952",
            "text": "@JewelsSoul Wish it was cool LOL"
        },
        {
            "author_id": "27989519",
            "created_at": "2011-07-22T21:38:15.000Z",
            "geo": {
                "place_id": "eec8e86da985fc44"
            },
            "id": "94521662648762368",
            "text": "@JewelsSoul I usualluy like the heat but like to go inside to where it is cool usually but it is 88 in the hou\u2026 (cont) http://deck.ly/~ahiOo"
        },
        {
            "author_id": "27989519",
            "created_at": "2011-07-22T21:36:09.000Z",
            "geo": {
                "place_id": "eec8e86da985fc44"
            },
            "id": "94521133625380864",
            "text": "@TaysLadybug well if the GD house doesn't cool soon I am gonna kill someone LOL"
        },
        {
            "author_id": "27989519",
            "created_at": "2011-07-22T21:35:45.000Z",
            "geo": {
                "place_id": "eec8e86da985fc44"
            },
            "id": "94521036229459968",
            "text": "@mond105 Yeah was too lazy to list everyone found a website that lists people that you tweeted the most or twe\u2026 (cont) http://deck.ly/~tWV3F"
        },
        {
            "author_id": "27989519",
            "created_at": "2011-07-22T21:33:46.000Z",
            "geo": {
                "place_id": "eec8e86da985fc44"
            },
            "id": "94520535979003905",
            "text": "#FF @wizard_radio"
        },
        {
            "author_id": "27989519",
            "created_at": "2011-07-22T21:32:25.000Z",
            "geo": {
                "place_id": "eec8e86da985fc44"
            },
            "id": "94520195971940352",
            "text": "@wizard_radio @TaylorRHicks"
        },
        {
            "author_id": "27989519",
            "created_at": "2011-07-22T21:28:06.000Z",
            "geo": {
                "place_id": "eec8e86da985fc44"
            },
            "id": "94519108107894784",
            "text": "@TaysLadybug  and now the temp went up to 88 in the house went up two degrees, thinking about looking into window units LOL"
        },
        {
            "author_id": "27989519",
            "created_at": "2011-07-22T21:27:26.000Z",
            "geo": {
                "place_id": "eec8e86da985fc44"
            },
            "id": "94518941073948672",
            "text": "@TaysLadybug guess what the guys for the air conditioner came back said that they had to make more holes in th\u2026 (cont) http://deck.ly/~Y4G2W"
        },
        {
            "author_id": "27989519",
            "created_at": "2011-07-22T21:26:33.000Z",
            "geo": {
                "place_id": "eec8e86da985fc44"
            },
            "id": "94518718922629121",
            "text": "#FF all my friends here LOL too lazy to type in all the names have to go get dinner now anyway so to all, Happy Friday!"
        },
        {
            "author_id": "27989519",
            "created_at": "2011-07-22T21:17:55.000Z",
            "geo": {
                "place_id": "eec8e86da985fc44"
            },
            "id": "94516545782419457",
            "text": "@TaysLadybug LOL"
        },
        {
            "author_id": "338163153",
            "created_at": "2011-07-22T21:15:55.000Z",
            "geo": {
                "place_id": "3645adf266c57704"
            },
            "id": "94516044697313280",
            "text": "cant wait for smackdown tonight i think @RandyOrton is gunna win the street fight with all of his aggression building up."
        },
        {
            "author_id": "36599370",
            "created_at": "2011-07-22T21:09:30.000Z",
            "geo": {
                "place_id": "eec8e86da985fc44"
            },
            "id": "94514430699778048",
            "text": "I'm at Walmart Supercenter (1540 Military Rd., LaSalle Center, Niagara Falls) w/ 2 others http://4sq.com/qjFjAm"
        },
        {
            "author_id": "27989519",
            "created_at": "2011-07-22T21:09:28.000Z",
            "geo": {
                "place_id": "eec8e86da985fc44"
            },
            "id": "94514419173822465",
            "text": "@PatPietrowski :)"
        },
        {
            "author_id": "27989519",
            "created_at": "2011-07-22T21:07:53.000Z",
            "geo": {
                "place_id": "eec8e86da985fc44"
            },
            "id": "94514021667061760",
            "text": "@PatPietrowski TY you too"
        },
        {
            "author_id": "218121199",
            "created_at": "2011-07-22T20:44:13.000Z",
            "geo": {
                "place_id": "3645adf266c57704"
            },
            "id": "94508065931542529",
            "text": "@TheKingNappy &lt;&lt;&lt; Hates on BF3 even though he has never experienced Battlefield at all...Talk about CoD fanboy!  Watch me tear him up 2nite!"
        },
        {
            "author_id": "218121199",
            "created_at": "2011-07-22T20:41:31.000Z",
            "geo": {
                "place_id": "3645adf266c57704"
            },
            "id": "94507386835963904",
            "text": "@Bigcountry77x &lt;&lt;&lt; If ya don't know now ya know.."
        },
        {
            "author_id": "15739357",
            "created_at": "2011-07-22T19:57:05.000Z",
            "geo": {
                "place_id": "eec8e86da985fc44"
            },
            "id": "94496203043123201",
            "text": "I'm at U.S. Customs and Immigration (Rainbow Bridge, Niagara Falls) w/ 2 others http://4sq.com/pVbQ2A"
        },
        {
            "author_id": "158172978",
            "created_at": "2011-07-22T19:56:38.000Z",
            "geo": {
                "place_id": "eec8e86da985fc44"
            },
            "id": "94496090694500353",
            "text": "Swimming shopping sleeping cleaning not in that order #funinthesun"
        },
        {
            "author_id": "17880088",
            "created_at": "2011-07-22T19:29:37.000Z",
            "geo": {
                "place_id": "eec8e86da985fc44"
            },
            "id": "94489294454001664",
            "text": "I'm at Sam's Club (5535 Porter Rd., Niagara Falls) http://4sq.com/ne0MIz"
        },
        {
            "author_id": "1649821",
            "created_at": "2011-07-22T19:22:45.000Z",
            "geo": {
                "place_id": "8c220f622f6c04d4"
            },
            "id": "94487564320391168",
            "text": "@kapgar @karlerikson he's as doomed as doomed can be. :)"
        },
        {
            "author_id": "218121199",
            "created_at": "2011-07-22T18:47:49.000Z",
            "geo": {
                "place_id": "3645adf266c57704"
            },
            "id": "94478774334267392",
            "text": "Hey @NateGouldsvGT My channel just passed yours ;)"
        },
        {
            "author_id": "218121199",
            "created_at": "2011-07-22T18:46:15.000Z",
            "geo": {
                "place_id": "3645adf266c57704"
            },
            "id": "94478378165481472",
            "text": "@TheKingNappy Sounds good..."
        },
        {
            "author_id": "158172978",
            "created_at": "2011-07-22T18:46:13.000Z",
            "geo": {
                "place_id": "eec8e86da985fc44"
            },
            "id": "94478370305347584",
            "text": "@EricSchug idk about that but I'm trying."
        },
        {
            "author_id": "21202486",
            "created_at": "2011-07-22T18:38:33.000Z",
            "geo": {
                "place_id": "eec8e86da985fc44"
            },
            "id": "94476440833232896",
            "text": "Guy in front of me just bought  $100 bottle of wine. Whoa. #liquorstoreadventures"
        },
        {
            "author_id": "248590879",
            "created_at": "2011-07-22T18:38:09.000Z",
            "geo": {
                "place_id": "8c220f622f6c04d4"
            },
            "id": "94476342233534464",
            "text": "I was raised to #neversaynever . I'm #beyondblessed , I #believeindreams and I #dreambig . #whatalife :)"
        },
        {
            "author_id": "158172978",
            "created_at": "2011-07-22T18:33:49.000Z",
            "geo": {
                "place_id": "eec8e86da985fc44"
            },
            "id": "94475250896601088",
            "text": "@EricSchug I haven't conquered mine yet. I'm loving twitter too."
        },
        {
            "author_id": "340023377",
            "created_at": "2011-07-22T18:19:12.000Z",
            "geo": {
                "place_id": "3645adf266c57704"
            },
            "id": "94471571997081601",
            "text": "@Mary__Lucas it was fun!! Love you!"
        },
        {
            "author_id": "50936351",
            "created_at": "2011-07-22T18:02:33.000Z",
            "geo": {
                "place_id": "eec8e86da985fc44"
            },
            "id": "94467379848937472",
            "text": "I'm not stoppin for you no matter what you do THIS IS #MYMOMENT"
        },
        {
            "author_id": "50936351",
            "created_at": "2011-07-22T18:02:07.000Z",
            "geo": {
                "place_id": "eec8e86da985fc44"
            },
            "id": "94467270570553344",
            "text": "@heathernewkirk there's nothing to #love but #love itself also DON'T CALL ME THAT"
        },
        {
            "author_id": "218121199",
            "created_at": "2011-07-22T17:35:52.000Z",
            "geo": {
                "place_id": "3645adf266c57704"
            },
            "id": "94460665070227457",
            "text": "@LethalEuphoria Sorry I missed your message bud"
        },
        {
            "author_id": "218121199",
            "created_at": "2011-07-22T17:35:21.000Z",
            "geo": {
                "place_id": "3645adf266c57704"
            },
            "id": "94460534426050560",
            "text": "http://t.co/Q5XsJZX SvenD|TV Tonight @ 8P.M. EST Feat. The Hardline Report Team [Nappyboy, DrakeStar, BigAl, BigCountry]!"
        },
        {
            "author_id": "13051142",
            "created_at": "2011-07-22T17:33:49.000Z",
            "geo": {
                "place_id": "eec8e86da985fc44"
            },
            "id": "94460150563356672",
            "text": "Next time I'm bringing a barrel.  @ Niagara Falls (American Side) http://instagr.am/p/IPzim/"
        },
        {
            "author_id": "17280269",
            "created_at": "2011-07-22T17:10:54.000Z",
            "geo": {
                "place_id": "8c220f622f6c04d4"
            },
            "id": "94454383089172480",
            "text": "State police charge two in car dealer warranty scam http://bit.ly/q2orGX via http://outside.in/14304"
        },
        {
            "author_id": "17280269",
            "created_at": "2011-07-22T17:10:54.000Z",
            "geo": {
                "place_id": "8c220f622f6c04d4"
            },
            "id": "94454382631989249",
            "text": "Congratulations to Kitty Lambert and Cheryle Rudd http://bit.ly/n2kUva via http://outside.in/14304"
        },
        {
            "author_id": "250320973",
            "created_at": "2011-07-22T17:00:11.000Z",
            "geo": {
                "place_id": "eec8e86da985fc44"
            },
            "id": "94451687837810688",
            "text": "#Canada delays up to one hour entering the u.s. on RAINBOW BRG EB between RIVER RD and NIAGARA ST in #NiagaraFalls,Ny as reported by dot"
        },
        {
            "author_id": "173632593",
            "created_at": "2011-07-22T16:51:28.000Z",
            "geo": {
                "place_id": "8c220f622f6c04d4"
            },
            "id": "94449494409752576",
            "text": "@GingerGeoffery i will as long as i can keep the ac running"
        },
        {
            "author_id": "17280269",
            "created_at": "2011-07-22T16:43:19.000Z",
            "geo": {
                "place_id": "8c220f622f6c04d4"
            },
            "id": "94447442539454464",
            "text": "Vol. They Aren\u2019t Nike\u2019s Or Adidas\u2019s, But I Keep\u2019m Clean: Trax Kmart Sneakers 1976 http://bit.ly/pte6kr via http://outside.in/14304"
        },
        {
            "author_id": "173632593",
            "created_at": "2011-07-22T16:24:28.000Z",
            "geo": {
                "place_id": "8c220f622f6c04d4"
            },
            "id": "94442697569484800",
            "text": "@DavidNelson86 get ready to practice"
        },
        {
            "author_id": "173632593",
            "created_at": "2011-07-22T16:09:47.000Z",
            "geo": {
                "place_id": "8c220f622f6c04d4"
            },
            "id": "94439001641074688",
            "text": "@JaySkurski i agree....teams are going to over pay for players bc they have to pay up to cap..."
        },
        {
            "author_id": "102252952",
            "created_at": "2011-07-22T16:06:50.000Z",
            "geo": {
                "place_id": "3645adf266c57704"
            },
            "id": "94438261388349440",
            "text": "Piano Recital Set For Saturday - http://bit.ly/nUQuW6 #Jamestown #NewYork"
        },
        {
            "author_id": "28464629",
            "created_at": "2011-07-22T15:30:22.000Z",
            "geo": {
                "place_id": "8c220f622f6c04d4"
            },
            "id": "94429083148107776",
            "text": "Eating lunch at 1130. Take that Patty (@ Chili's) http://4sq.com/qOXWdU"
        },
        {
            "author_id": "173632593",
            "created_at": "2011-07-22T15:15:38.000Z",
            "geo": {
                "place_id": "8c220f622f6c04d4"
            },
            "id": "94425375597273089",
            "text": "@LeopoldsIpod so then sabres make a decision enroth long term...miller gone"
        },
        {
            "author_id": "173632593",
            "created_at": "2011-07-22T15:10:16.000Z",
            "geo": {
                "place_id": "8c220f622f6c04d4"
            },
            "id": "94424024620351488",
            "text": "@LeopoldsIpod do u know how many yrs left on millers contract"
        },
        {
            "author_id": "59572917",
            "created_at": "2011-07-22T14:58:54.000Z",
            "geo": {
                "place_id": "8c220f622f6c04d4"
            },
            "id": "94421165442990082",
            "text": "OD hot today in These uniforms !!"
        },
        {
            "author_id": "234550994",
            "created_at": "2011-07-22T14:52:51.000Z",
            "geo": {
                "place_id": "eec8e86da985fc44"
            },
            "id": "94419643141337089",
            "text": "I need both my tattoos covered up with another tattoo hmmm maybe my birthday weekend"
        },
        {
            "author_id": "173632593",
            "created_at": "2011-07-22T14:49:18.000Z",
            "geo": {
                "place_id": "8c220f622f6c04d4"
            },
            "id": "94418750169821184",
            "text": "@SarahJess7 im just happy u renewed ur sabres...btw hopefully the wine wasnt boones farm cuz that would ruin my day"
        },
        {
            "author_id": "234550994",
            "created_at": "2011-07-22T13:47:18.000Z",
            "geo": {
                "place_id": "eec8e86da985fc44"
            },
            "id": "94403146092249089",
            "text": "I dislike being black I wake up all oily and what not"
        },
        {
            "author_id": "91793627",
            "created_at": "2011-07-22T13:05:51.000Z",
            "geo": {
                "place_id": "87905a5a3a5b8644"
            },
            "id": "94392714824663041",
            "text": "@kidfromkidnplay do you still have the number for Ex Con Catering or Angina Williams? #houseparty3 #MyFav"
        },
        {
            "author_id": "50737331",
            "created_at": "2011-07-22T11:02:03.000Z",
            "geo": {
                "place_id": "eec8e86da985fc44"
            },
            "id": "94361558423044096",
            "text": "Constr. work,work on underground cables on I-190 both directions btw Robert Moses State Pkwy (Niagara Falls) and Rte ...http://bit.ly/6dAFiP"
        },
        {
            "author_id": "50706690",
            "created_at": "2011-07-22T11:01:59.000Z",
            "geo": {
                "place_id": "eec8e86da985fc44"
            },
            "id": "94361542132383744",
            "text": "Constr. work,work on underground cables on I-190 both directions btw Robert Moses State Pkwy (Niagara Falls) and Rte ...http://bit.ly/5Xuc69"
        },
        {
            "author_id": "50737331",
            "created_at": "2011-07-22T11:01:33.000Z",
            "geo": {
                "place_id": "3645adf266c57704"
            },
            "id": "94361434691088384",
            "text": "Constr. work on 951C; Washington both directions btw Washington St; NY 60; West 6th St; NY 394; START Rte  Washington...http://bit.ly/6dAFiP"
        },
        {
            "author_id": "50706690",
            "created_at": "2011-07-22T11:01:33.000Z",
            "geo": {
                "place_id": "3645adf266c57704"
            },
            "id": "94361431876714496",
            "text": "Constr. work on 951C; Washington both directions btw Washington St; NY 60; West 6th St; NY 394; START Rte  Washington...http://bit.ly/5Xuc69"
        },
        {
            "author_id": "36861587",
            "created_at": "2011-07-22T10:44:16.000Z",
            "geo": {
                "place_id": "eec8e86da985fc44"
            },
            "id": "94357083650129920",
            "text": "@bettywantsabs Happy birthday. Great idea taking the day off."
        },
        {
            "author_id": "158172978",
            "created_at": "2011-07-22T09:34:53.000Z",
            "geo": {
                "place_id": "8c220f622f6c04d4"
            },
            "id": "94339622120857600",
            "text": "Friday pheww took you forever to get here #longestweekever"
        },
        {
            "author_id": "158172978",
            "created_at": "2011-07-22T09:32:58.000Z",
            "geo": {
                "place_id": "8c220f622f6c04d4"
            },
            "id": "94339140287606784",
            "text": "@MAGrabek have you tried the peal and stick nail polish comes in strips no painting just stick it on your nail and peel backing off"
        },
        {
            "author_id": "330953859",
            "created_at": "2011-07-22T09:10:43.000Z",
            "geo": {
                "place_id": "eec8e86da985fc44"
            },
            "id": "94333540728193024",
            "text": "My left side and right side are good and evil. Problem is I'm right handed.."
        },
        {
            "author_id": "50936351",
            "created_at": "2011-07-22T07:27:38.000Z",
            "geo": {
                "place_id": "eec8e86da985fc44"
            },
            "id": "94307600765698048",
            "text": "@deasto #noh8"
        },
        {
            "author_id": "114844148",
            "created_at": "2011-07-22T07:00:42.000Z",
            "geo": {
                "place_id": "87905a5a3a5b8644"
            },
            "id": "94300821780570113",
            "text": "Senior Accounting Clerk - Customer Ac... - #Olean , NY (http://tinyurl.com/3uj7qu6) Get Accounting Jobs #Accounting #jobs #job #GetAllJobs"
        },
        {
            "author_id": "338163153",
            "created_at": "2011-07-22T06:44:31.000Z",
            "geo": {
                "place_id": "3645adf266c57704"
            },
            "id": "94296747131682817",
            "text": "well hottt G.N. ppl"
        },
        {
            "author_id": "17880088",
            "created_at": "2011-07-22T06:43:13.000Z",
            "geo": {
                "place_id": "eec8e86da985fc44"
            },
            "id": "94296422559662080",
            "text": "@joshbrochelle you misspelled annoying but thank you! #FF @joshbrochelle"
        },
        {
            "author_id": "102252952",
            "created_at": "2011-07-22T06:34:10.000Z",
            "geo": {
                "place_id": "3645adf266c57704"
            },
            "id": "94294142481473538",
            "text": "Area Police Reports - http://bit.ly/qZCk7E #Clymer #NewYork"
        },
        {
            "author_id": "102252952",
            "created_at": "2011-07-22T06:31:49.000Z",
            "geo": {
                "place_id": "3645adf266c57704"
            },
            "id": "94293551021690881",
            "text": "Niagara U. Names Spring Dean's List - http://bit.ly/r0Mp1u #Allegany #NewYork"
        },
        {
            "author_id": "27989519",
            "created_at": "2011-07-22T05:43:16.000Z",
            "geo": {
                "place_id": "eec8e86da985fc44"
            },
            "id": "94281334595387392",
            "text": "good night"
        },
        {
            "author_id": "27989519",
            "created_at": "2011-07-22T05:43:05.000Z",
            "geo": {
                "place_id": "eec8e86da985fc44"
            },
            "id": "94281288990732288",
            "text": "@hookedonhicks good night"
        },
        {
            "author_id": "22163546",
            "created_at": "2011-07-22T05:18:43.000Z",
            "geo": {
                "place_id": "eec8e86da985fc44"
            },
            "id": "94275156255580160",
            "text": "RT @GirlDictionary Sometimes her &quot;leave me alone&quot; really means &quot;come after me&quot;, &quot;I'm (cont) http://tl.gd/bsls1e"
        },
        {
            "author_id": "22163546",
            "created_at": "2011-07-22T05:14:47.000Z",
            "geo": {
                "place_id": "eec8e86da985fc44"
            },
            "id": "94274165854580736",
            "text": "I have been whiny!!! My god, I'm sorry everyone."
        },
        {
            "author_id": "12745992",
            "created_at": "2011-07-22T05:14:26.000Z",
            "geo": {
                "place_id": "87905a5a3a5b8644"
            },
            "id": "94274078109728768",
            "text": "I think it might be a trillion degrees in my house."
        },
        {
            "author_id": "22163546",
            "created_at": "2011-07-22T05:01:47.000Z",
            "geo": {
                "place_id": "eec8e86da985fc44"
            },
            "id": "94270896059056129",
            "text": "Snuggled up with a bag of ice since sleeping in the cool livingroom is out of the question..."
        },
        {
            "author_id": "338163153",
            "created_at": "2011-07-22T04:48:04.000Z",
            "geo": {
                "place_id": "3645adf266c57704"
            },
            "id": "94267441953247232",
            "text": "@WWEUniverse @SteveAustinBSR who does he think was his best opponents in the ring"
        },
        {
            "author_id": "3479601",
            "created_at": "2011-07-22T04:47:59.000Z",
            "geo": {
                "place_id": "eec8e86da985fc44"
            },
            "id": "94267423557033984",
            "text": "@jennapesq No I am not currently wearing swim trunks."
        },
        {
            "author_id": "338163153",
            "created_at": "2011-07-22T04:43:57.000Z",
            "geo": {
                "place_id": "3645adf266c57704"
            },
            "id": "94266405108727808",
            "text": "@TedDiBiase lol why nott unless he doesnt like you right haha"
        },
        {
            "author_id": "338163153",
            "created_at": "2011-07-22T04:42:40.000Z",
            "geo": {
                "place_id": "3645adf266c57704"
            },
            "id": "94266085771190272",
            "text": "wowwwwww  madddd gay....its so boring- lol"
        },
        {
            "author_id": "338163153",
            "created_at": "2011-07-22T04:37:14.000Z",
            "geo": {
                "place_id": "3645adf266c57704"
            },
            "id": "94264716867796992",
            "text": "wow it really hott dont kno what to do....its 12:30 and there is nuthin to do"
        },
        {
            "author_id": "52103637",
            "created_at": "2011-07-22T04:32:54.000Z",
            "geo": {
                "place_id": "eec8e86da985fc44"
            },
            "id": "94263625971273728",
            "text": "Good time in the ac :)"
        },
        {
            "author_id": "338163153",
            "created_at": "2011-07-22T04:30:37.000Z",
            "geo": {
                "place_id": "3645adf266c57704"
            },
            "id": "94263051246764032",
            "text": "@ShaneHelmsCom witch one of your gimmick do you think was your favorite while you were wrestling...."
        },
        {
            "author_id": "234550994",
            "created_at": "2011-07-22T04:24:31.000Z",
            "geo": {
                "place_id": "eec8e86da985fc44"
            },
            "id": "94261518471925760",
            "text": "Whoa dere"
        },
        {
            "author_id": "27989519",
            "created_at": "2011-07-22T04:23:51.000Z",
            "geo": {
                "place_id": "eec8e86da985fc44"
            },
            "id": "94261348535513089",
            "text": "@hookedonhicks  maybe  not U but he will certainly live without me LOL"
        },
        {
            "author_id": "325844978",
            "created_at": "2011-07-22T04:18:27.000Z",
            "geo": {
                "place_id": "eec8e86da985fc44"
            },
            "id": "94259989182545920",
            "text": "@kaaitlinmcguire go away kid"
        },
        {
            "author_id": "338163153",
            "created_at": "2011-07-22T04:17:48.000Z",
            "geo": {
                "place_id": "3645adf266c57704"
            },
            "id": "94259824845529089",
            "text": "so do u guys watch tna and have seen stings latest gimmick i think its one of the best ones....and kurt and sting make a great team.. :)"
        },
        {
            "author_id": "27989519",
            "created_at": "2011-07-22T04:06:14.000Z",
            "geo": {
                "place_id": "eec8e86da985fc44"
            },
            "id": "94256916343164928",
            "text": "@hookedonhicks I can't make any of the shows either not sure about chat next weeks schedule don't come out ti\u2026 (cont) http://deck.ly/~P6Nfu"
        },
        {
            "author_id": "234550994",
            "created_at": "2011-07-22T04:02:41.000Z",
            "geo": {
                "place_id": "eec8e86da985fc44"
            },
            "id": "94256021387755521",
            "text": "@chrisbrown I b hitting home runs while you still on 2nd base"
        },
        {
            "author_id": "27989519",
            "created_at": "2011-07-22T03:58:53.000Z",
            "geo": {
                "place_id": "eec8e86da985fc44"
            },
            "id": "94255064113360897",
            "text": "@hookedonhicks Did you work today?"
        },
        {
            "author_id": "234550994",
            "created_at": "2011-07-22T03:54:41.000Z",
            "geo": {
                "place_id": "eec8e86da985fc44"
            },
            "id": "94254007475908608",
            "text": "I'm just doin me & you could never understand it"
        },
        {
            "author_id": "234550994",
            "created_at": "2011-07-22T03:50:57.000Z",
            "geo": {
                "place_id": "eec8e86da985fc44"
            },
            "id": "94253068195074048",
            "text": "Baby girl I'm askin for a night of passion \ue327"
        },
        {
            "author_id": "234550994",
            "created_at": "2011-07-22T03:47:46.000Z",
            "geo": {
                "place_id": "eec8e86da985fc44"
            },
            "id": "94252268928503808",
            "text": "Shake that"
        },
        {
            "author_id": "234550994",
            "created_at": "2011-07-22T03:29:56.000Z",
            "geo": {
                "place_id": "eec8e86da985fc44"
            },
            "id": "94247780691869697",
            "text": "#np Usher- #followme how ironic"
        },
        {
            "author_id": "173632593",
            "created_at": "2011-07-22T03:24:15.000Z",
            "geo": {
                "place_id": "8c220f622f6c04d4"
            },
            "id": "94246349440167937",
            "text": "@LCLB63 i wish i was sitting at center ice its so hot here"
        },
        {
            "author_id": "234550994",
            "created_at": "2011-07-22T03:21:40.000Z",
            "geo": {
                "place_id": "eec8e86da985fc44"
            },
            "id": "94245700015104000",
            "text": "#np Maroon 5- Moves Like Jagger"
        },
        {
            "author_id": "173632593",
            "created_at": "2011-07-22T03:02:26.000Z",
            "geo": {
                "place_id": "8c220f622f6c04d4"
            },
            "id": "94240858471280641",
            "text": "@Cherylfoy81 i agree"
        },
        {
            "author_id": "173632593",
            "created_at": "2011-07-22T02:57:03.000Z",
            "geo": {
                "place_id": "8c220f622f6c04d4"
            },
            "id": "94239502767370240",
            "text": "@thecfbgirl with all this nfl nonsense really looking forward to college football"
        },
        {
            "author_id": "173632593",
            "created_at": "2011-07-22T02:51:03.000Z",
            "geo": {
                "place_id": "8c220f622f6c04d4"
            },
            "id": "94237994889912324",
            "text": "@thecfbgirl yes it is....ut our first taste of football...plus i like when they interview HOF inductees during game"
        },
        {
            "author_id": "27989519",
            "created_at": "2011-07-22T02:31:27.000Z",
            "geo": {
                "place_id": "eec8e86da985fc44"
            },
            "id": "94233062203863040",
            "text": "@seor they air conditioner guys came back today said they intalled a new wire in the furnace and installed \u2026 (cont) http://deck.ly/~75xFu"
        },
        {
            "author_id": "234550994",
            "created_at": "2011-07-22T02:30:31.000Z",
            "geo": {
                "place_id": "eec8e86da985fc44"
            },
            "id": "94232826236510208",
            "text": "I listen to some wild music"
        },
        {
            "author_id": "234550994",
            "created_at": "2011-07-22T02:26:18.000Z",
            "geo": {
                "place_id": "eec8e86da985fc44"
            },
            "id": "94231767023755264",
            "text": "#ithoughtyoulookedgood until I seen your shoes #burn"
        },
        {
            "author_id": "234550994",
            "created_at": "2011-07-22T02:24:59.000Z",
            "geo": {
                "place_id": "eec8e86da985fc44"
            },
            "id": "94231435422072832",
            "text": "#everybodyhasthat1follower that they wanna make love to!!"
        },
        {
            "author_id": "36861587",
            "created_at": "2011-07-22T02:18:26.000Z",
            "geo": {
                "place_id": "eec8e86da985fc44"
            },
            "id": "94229786532130816",
            "text": "well I survived the record breaking heat. Admittedly 4 hours of it at the Y with its AC."
        },
        {
            "author_id": "338163153",
            "created_at": "2011-07-22T02:13:43.000Z",
            "geo": {
                "place_id": "3645adf266c57704"
            },
            "id": "94228599816732672",
            "text": "@plies lol shoulda known that was gunna happen lmao"
        },
        {
            "author_id": "17880088",
            "created_at": "2011-07-22T02:07:29.000Z",
            "geo": {
                "place_id": "eec8e86da985fc44"
            },
            "id": "94227030459154433",
            "text": "I'm at Bear Cave (2873 Macklem Avenue, Niagara Falls) http://4sq.com/mPNK0Y"
        },
        {
            "author_id": "3479601",
            "created_at": "2011-07-22T01:59:28.000Z",
            "geo": {
                "place_id": "eec8e86da985fc44"
            },
            "id": "94225014622134272",
            "text": "@littering_and I sleep with a cat at the head of my bed. #thecatisparanoid"
        },
        {
            "author_id": "28640442",
            "created_at": "2011-07-22T01:59:20.000Z",
            "geo": {
                "place_id": "eec8e86da985fc44"
            },
            "id": "94224979884904448",
            "text": "watching #nyink tonight, SOLELY for @JennaMorasca"
        },
        {
            "author_id": "3479601",
            "created_at": "2011-07-22T01:58:07.000Z",
            "geo": {
                "place_id": "eec8e86da985fc44"
            },
            "id": "94224673906233344",
            "text": "I make noise this Wednesday at Sugar City. Time: 7PM Price: $5"
        },
        {
            "author_id": "19640535",
            "created_at": "2011-07-22T01:56:06.000Z",
            "geo": {
                "place_id": "8c220f622f6c04d4"
            },
            "id": "94224164474454019",
            "text": "@malshayie \u0646\u0641\u0633 \u0627\u0644\u0648\u0636\u0639 \u0628\u0627\u0633\u062a\u062b\u0627\u0621 \u0627\u0646 \u0627\u0644\u0627\u0634\u064a\u0627\u0621 \u0645\u0627 \u062a\u0631\u062c\u0639 \u0644\u0645\u0643\u0627\u0646\u0647\u0627 \u062a\u0646\u062d\u0627\u0633 \u0641\u064a \u0645\u0643\u0627\u0646 \u062b\u0627\u0646\u064a"
        },
        {
            "author_id": "3479601",
            "created_at": "2011-07-22T01:51:59.000Z",
            "geo": {
                "place_id": "eec8e86da985fc44"
            },
            "id": "94223130335256576",
            "text": "@torance27 You are crazy man!"
        },
        {
            "author_id": "28640442",
            "created_at": "2011-07-22T01:41:43.000Z",
            "geo": {
                "place_id": "eec8e86da985fc44"
            },
            "id": "94220544710418432",
            "text": "lol, did we just get audio of rachel peeing? #bb13"
        },
        {
            "author_id": "28640442",
            "created_at": "2011-07-22T01:24:55.000Z",
            "geo": {
                "place_id": "eec8e86da985fc44"
            },
            "id": "94216319733473280",
            "text": "LOL dominic was home-schooled? NO WONDER HE'S A VIRGIN #bb13"
        },
        {
            "author_id": "28640442",
            "created_at": "2011-07-22T01:22:41.000Z",
            "geo": {
                "place_id": "eec8e86da985fc44"
            },
            "id": "94215756723662849",
            "text": "lol, remember how porche is technically on the show? or should i say in the house, because you never see her on tv #bb13"
        },
        {
            "author_id": "28640442",
            "created_at": "2011-07-22T01:18:23.000Z",
            "geo": {
                "place_id": "eec8e86da985fc44"
            },
            "id": "94214672563187712",
            "text": "brendan needs to stop being a douche. him and rachel are so frusturating #bb13"
        },
        {
            "author_id": "28640442",
            "created_at": "2011-07-22T01:13:18.000Z",
            "geo": {
                "place_id": "eec8e86da985fc44"
            },
            "id": "94213397347971073",
            "text": "i love cassi's bathing suit #bb13"
        },
        {
            "author_id": "28640442",
            "created_at": "2011-07-22T01:12:43.000Z",
            "geo": {
                "place_id": "eec8e86da985fc44"
            },
            "id": "94213248898965504",
            "text": "if i ever cried on big brother, i think they would kick me off because of how gross i look #bb13"
        },
        {
            "author_id": "28640442",
            "created_at": "2011-07-22T01:11:30.000Z",
            "geo": {
                "place_id": "eec8e86da985fc44"
            },
            "id": "94212941959798785",
            "text": "jordan is such a baby angel #bb13"
        },
        {
            "author_id": "17880088",
            "created_at": "2011-07-22T01:11:21.000Z",
            "geo": {
                "place_id": "eec8e86da985fc44"
            },
            "id": "94212904194277376",
            "text": "@PAT_terns on my way."
        },
        {
            "author_id": "17880088",
            "created_at": "2011-07-22T01:08:23.000Z",
            "geo": {
                "place_id": "eec8e86da985fc44"
            },
            "id": "94212156299554817",
            "text": "@nickcottrell def!"
        },
        {
            "author_id": "17880088",
            "created_at": "2011-07-22T01:07:56.000Z",
            "geo": {
                "place_id": "eec8e86da985fc44"
            },
            "id": "94212046358450176",
            "text": "@PAT_terns you tryin' to shower with me pat?"
        },
        {
            "author_id": "17880088",
            "created_at": "2011-07-22T01:04:29.000Z",
            "geo": {
                "place_id": "eec8e86da985fc44"
            },
            "id": "94211175918743553",
            "text": "@PAT_terns I was so ridiculously warm at the time, that I didn't want to wait until I got all the way home."
        },
        {
            "author_id": "17880088",
            "created_at": "2011-07-22T01:01:40.000Z",
            "geo": {
                "place_id": "eec8e86da985fc44"
            },
            "id": "94210465978261504",
            "text": "@nickcottrell friggin jealous."
        },
        {
            "author_id": "17880088",
            "created_at": "2011-07-22T01:01:29.000Z",
            "geo": {
                "place_id": "eec8e86da985fc44"
            },
            "id": "94210421963239424",
            "text": "@PAT_terns I was on a bike ride and wasn't home."
        },
        {
            "author_id": "218121199",
            "created_at": "2011-07-22T00:58:38.000Z",
            "geo": {
                "place_id": "3645adf266c57704"
            },
            "id": "94209703990665216",
            "text": "http://t.co/Q4CrhYd - Billkeyz show starting now!  Come check it out people!  Billkeyz, TheUgoogilzer, Nategould & Myself will all b guests!"
        },
        {
            "author_id": "17880088",
            "created_at": "2011-07-22T00:58:36.000Z",
            "geo": {
                "place_id": "eec8e86da985fc44"
            },
            "id": "94209694280859648",
            "text": "@nickcottrell you have a pool?!"
        },
        {
            "author_id": "17880088",
            "created_at": "2011-07-22T00:56:34.000Z",
            "geo": {
                "place_id": "eec8e86da985fc44"
            },
            "id": "94209182709989377",
            "text": "Have a pool or a shower you are willing to share? Hmu."
        },
        {
            "author_id": "338163153",
            "created_at": "2011-07-22T00:48:32.000Z",
            "geo": {
                "place_id": "3645adf266c57704"
            },
            "id": "94207160648601600",
            "text": "@ShawnMichaels_ whts up.."
        },
        {
            "author_id": "338163153",
            "created_at": "2011-07-22T00:44:58.000Z",
            "geo": {
                "place_id": "3645adf266c57704"
            },
            "id": "94206263289839616",
            "text": "@TheRock lol"
        },
        {
            "author_id": "17280269",
            "created_at": "2011-07-22T00:41:23.000Z",
            "geo": {
                "place_id": "8c220f622f6c04d4"
            },
            "id": "94205363095744513",
            "text": "Rabid raccoon caught in Niagara Falls http://bit.ly/pSs3Yg via http://outside.in/14304"
        },
        {
            "author_id": "338163153",
            "created_at": "2011-07-22T00:39:43.000Z",
            "geo": {
                "place_id": "3645adf266c57704"
            },
            "id": "94204943141060609",
            "text": "@McCoolMFan4ever yea im pretty sure if shawn michaels was madd at me for it than i would be pretty upset too but i was juss talkin"
        },
        {
            "author_id": "338163153",
            "created_at": "2011-07-22T00:38:13.000Z",
            "geo": {
                "place_id": "3645adf266c57704"
            },
            "id": "94204565523660800",
            "text": "@jamesgang4lyfe @ShawnMichaels_ well yea it would be could to fall bck on cuz if i dont make it than wht do i do if i didnt go to college"
        },
        {
            "author_id": "17880088",
            "created_at": "2011-07-22T00:30:49.000Z",
            "geo": {
                "place_id": "eec8e86da985fc44"
            },
            "id": "94202705622482946",
            "text": "I'm at Whirlpool State Park (Whirlpool State Park, Niagara Falls) http://4sq.com/oJAzPI"
        },
        {
            "author_id": "80434007",
            "created_at": "2011-07-22T00:21:13.000Z",
            "geo": {
                "place_id": "eec8e86da985fc44"
            },
            "id": "94200289443319808",
            "text": "I'm at Niagara Falls State Park (300 Prospect St, Niagara Falls) http://4sq.com/oWF0vk"
        }
    ],
    "includes": {
        "places": [
            {
                "country_code": "US",
                "full_name": "Niagara Falls, NY",
                "id": "eec8e86da985fc44"
            },
            {
                "country_code": "US",
                "full_name": "Jamestown, NY",
                "id": "3645adf266c57704"
            },
            {
                "country_code": "US",
                "full_name": "Niagara, NY",
                "id": "8c220f622f6c04d4"
            },
            {
                "country_code": "US",
                "full_name": "Olean, NY",
                "id": "87905a5a3a5b8644"
            }
        ]
    },
    "meta": {
        "newest_id": "94555699404742656",
        "oldest_id": "94200289443319808",
        "result_count": 143
    }
}